LICENSE
README.rst
setup.py
tipoinstalacion/__init__.py
tipoinstalacion/models.py
tipoinstalacion.egg-info/PKG-INFO
tipoinstalacion.egg-info/SOURCES.txt
tipoinstalacion.egg-info/dependency_links.txt
tipoinstalacion.egg-info/top_level.txt