Metadata-Version: 2.1
Name: tipoinstalacion
Version: 1.0.1
Summary: Libreria para calcular de forma automática el Tipo de Instalacion (TI)
Home-page: https://github.com/gisce/tipoinstalacion
Author: GISCE-TI, S.L.
Author-email: devel@gisce.net
License: MIT
License-File: LICENSE
